wagtail_placeholder_images/__init__.py
wagtail_placeholder_images/mixins.py
wagtail_placeholder_images/version.py
wagtail_placeholder_images-0.1.1.dist-info/METADATA
wagtail_placeholder_images-0.1.1.dist-info/WHEEL
wagtail_placeholder_images-0.1.1.dist-info/top_level.txt
wagtail_placeholder_images-0.1.1.dist-info/RECORD
