Metadata-Version: 2.1
Name: wagtail-placeholder-images
Version: 0.1.1
Summary: Adds ability to use placeholder images for local development
Home-page: UNKNOWN
Author: Andreas Bernacca
Author-email: ante.bernacca@gmail.com
License: MIT License
Platform: UNKNOWN
Classifier: Environment :: Web Environment
Classifier: Intended Audience :: Developers
Classifier: Operating System :: OS Independent
Classifier: Programming Language :: Python
Classifier: Programming Language :: Python :: 3
Classifier: Programming Language :: Python :: 3.5
Classifier: Programming Language :: Python :: 3.6
Classifier: Programming Language :: Python :: 3.7
Classifier: Programming Language :: Python :: 3.8
Classifier: Framework :: Django
Classifier: License :: OSI Approved :: MIT License
Requires-Dist: wagtail (>=2.7)
Provides-Extra: testing
Requires-Dist: black ; extra == 'testing'
